flagwaver4/__init__.py
flagwaver4/__main__.py
flagwaver4/arduino.py
flagwaver4/flagwaver4.py
flagwaver4/interface.py
flagwaver4/runserver.py
flagwaver4/vector_math.py
flagwaver4/examples/detailed.py
flagwaver4/examples/realdata.py
flagwaver4/examples/simple.py
flagwaver4/examples/simulated.py
flagwaver4/static/jquery-3.1.1.min.js
flagwaver4/static/math.js
flagwaver4/static/css/bootstrap-toggle.min.css
flagwaver4/static/css/css.css
flagwaver4/static/css/flagwaver-ui.css
flagwaver4/static/css/normalize.min.css
flagwaver4/static/css/img/1024px-Flag_of_Egypt.svg.png
flagwaver4/static/css/img/18835679_10158749079520627_6120704423965528759_n.jpg
flagwaver4/static/css/img/Africa-Egypt-and-the-Nile-Pyraminds-MH.jpg
flagwaver4/static/css/img/Sky_over_Washington_Monument-1600x1200px.jpg
flagwaver4/static/css/img/Sky_over_Washington_Monument-480x640px.jpg
flagwaver4/static/css/img/Sky_over_Washington_Monument-800x600px.jpg
flagwaver4/static/css/img/fullscreen.png
flagwaver4/static/css/img/grit.png
flagwaver4/static/css/img/san3a.png
flagwaver4/static/css/img/texture1.png
flagwaver4/static/js/1024px-Flag_of_Egypt.svg.png
flagwaver4/static/js/bootstrap-toggle.min.js
flagwaver4/static/js/flagwaver-ui.js
flagwaver4/static/js/flagwaver.js
flagwaver4/static/js/hashvars.js
flagwaver4/static/js/jquery-1.11.1.min.js
flagwaver4/static/js/jquery-1.12.4.min.js
flagwaver4/static/js/loader.js
flagwaver4/static/js/modernizr.custom.95719.js
flagwaver4/static/js/rivets.bundled.min.js
flagwaver4/static/js/socket.io.js
flagwaver4/static/js/three.min.js
flagwaver4/static/sounds/2.mp3
flagwaver4/static/sounds/ambient.ogg
flagwaver4/static/sounds/flapping.mp3
flagwaver4/static/sounds/hover.mp3
flagwaver4/static/sounds/intro.mp3
flagwaver4/static/sounds/silence.mp3
flagwaver4/static/sounds/wind1.mp3
flagwaver4/templates/main.html
flagwaver4-1.0.0.dist-info/METADATA
flagwaver4-1.0.0.dist-info/WHEEL
flagwaver4-1.0.0.dist-info/top_level.txt
flagwaver4-1.0.0.dist-info/RECORD
