Metadata-Version: 2.1
Name: flagwaver4
Version: 1.0.0
Summary: UNKNOWN
Home-page: UNKNOWN
License: UNKNOWN
Platform: UNKNOWN
Requires-Python: >=3
Requires-Dist: flask
Requires-Dist: flask-socketio
Requires-Dist: pyserial
Requires-Dist: numpy
Requires-Dist: matplotlib
Requires-Dist: requests
